ephysiopy/__about__.py
ephysiopy/__init__.py
ephysiopy/axona/__init__.py
ephysiopy/axona/axonaIO.py
ephysiopy/axona/file_headers.py
ephysiopy/axona/tetrode_dict.py
ephysiopy/axona/tintcolours.py
ephysiopy/common/__init__.py
ephysiopy/common/binning.py
ephysiopy/common/ephys_generic.py
ephysiopy/common/fieldcalcs.py
ephysiopy/common/mle_von_mises_vals.py
ephysiopy/common/phasecoding.py
ephysiopy/common/rhythmicity.py
ephysiopy/common/spikecalcs.py
ephysiopy/common/statscalcs.py
ephysiopy/common/utils.py
ephysiopy/format_converters/OE_Axona.py
ephysiopy/format_converters/OE_numpy.py
ephysiopy/format_converters/__init__.py
ephysiopy/io/__init__.py
ephysiopy/io/recording.py
ephysiopy/openephys2py/KiloSort.py
ephysiopy/openephys2py/OESettings.py
ephysiopy/openephys2py/__init__.py
ephysiopy/tests/__init__.py
ephysiopy/tests/conftest.py
ephysiopy/tests/test_axona_headers.py
ephysiopy/tests/test_axona_io.py
ephysiopy/tests/test_binning.py
ephysiopy/tests/test_dacq2py.py
ephysiopy/tests/test_ephys_generic.py
ephysiopy/tests/test_fieldcalcs.py
ephysiopy/tests/test_openephys.py
ephysiopy/tests/test_phasecoding.py
ephysiopy/tests/test_rhythmicity.py
ephysiopy/tests/test_spikecalcs.py
ephysiopy/tests/test_statscalcs.py
ephysiopy/tests/test_utils.py
ephysiopy/visualise/__init__.py
ephysiopy/visualise/plotting.py
ephysiopy-2.0.55.dist-info/LICENSE
ephysiopy-2.0.55.dist-info/METADATA
ephysiopy-2.0.55.dist-info/WHEEL
ephysiopy-2.0.55.dist-info/top_level.txt
ephysiopy-2.0.55.dist-info/RECORD
