Metadata-Version: 2.2
Name: ephysiopy
Version: 2.0.55
Summary: Analysis of electrophysiology data
Home-page: https://github.com/rhayman/ephysiopy
Author: Robin Hayman
Author-email: robin.hayman@gmail.com
Classifier: Programming Language :: Python :: 3
Classifier: License :: OSI Approved :: MIT License
Classifier: Operating System :: OS Independent
Requires-Python: >=3.7
License-File: LICENSE
Requires-Dist: numpy
Requires-Dist: scipy
Requires-Dist: matplotlib
Requires-Dist: scikit-learn
Requires-Dist: astropy
Requires-Dist: scikit-image
Requires-Dist: pandas
Requires-Dist: h5py
Dynamic: author
Dynamic: author-email
Dynamic: classifier
Dynamic: description
Dynamic: description-content-type
Dynamic: home-page
Dynamic: requires-dist
Dynamic: requires-python
Dynamic: summary
